prlsnapshotter/__init__.py
prlsnapshotter/config.py
prlsnapshotter/prlsnapshotter.py
prlsnapshotter-0.0.4.dist-info/METADATA
prlsnapshotter-0.0.4.dist-info/WHEEL
prlsnapshotter-0.0.4.dist-info/entry_points.txt
prlsnapshotter-0.0.4.dist-info/top_level.txt
prlsnapshotter-0.0.4.dist-info/RECORD
