Metadata-Version: 2.1
Name: prlsnapshotter
Version: 0.0.4
Summary: Snapshotting parallels on command line and create machine by template.
Home-page: https://github.com/marcwimmer/prlsnapshotter
Author: Marc-Christian Wimmer
Author-email: marc@itewimmer.de
License: MIT
Platform: UNKNOWN
Classifier: License :: OSI Approved :: MIT License
Classifier: Programming Language :: Python
Classifier: Programming Language :: Python :: 3
Classifier: Programming Language :: Python :: 3.6
Classifier: Programming Language :: Python :: Implementation :: CPython
Classifier: Programming Language :: Python :: Implementation :: PyPy
Requires-Python: >=3.6.0
Requires-Dist: click
Requires-Dist: inquirer
Requires-Dist: arrow
Requires-Dist: pathlib
